CigarBreaker/CigarBreaker.py
CigarBreaker/__init__.py
FastaTransformer/FastaTransformer.py
FastaTransformer/__init__.py
FastaTransformer-0.0.14.dist-info/METADATA
FastaTransformer-0.0.14.dist-info/WHEEL
FastaTransformer-0.0.14.dist-info/top_level.txt
FastaTransformer-0.0.14.dist-info/RECORD
