Metadata-Version: 2.1
Name: FastaTransformer
Version: 0.0.14
Summary: This package helps resolve bioprogramming problems
Home-page: https://github.com/Global-ASFV-Research-Alliance/FastaTransformer
Author: MDinhobl
Author-email: markdinhobl@gmail.com
Project-URL: Bug Tracker, https://github.com/Global-ASFV-Research-Alliance/FastaTransformer
Classifier: Programming Language :: Python :: 3
Classifier: License :: OSI Approved :: MIT License
Classifier: Operating System :: OS Independent
Requires-Python: >=3.6
